README.md
setup.py
webdi/__init__.py
webdi/container.py
webdi/py.typed
webdi.egg-info/PKG-INFO
webdi.egg-info/SOURCES.txt
webdi.egg-info/dependency_links.txt
webdi.egg-info/not-zip-safe
webdi.egg-info/top_level.txt