Metadata-Version: 2.1
Name: webdi
Version: 0.1.1
Summary: A library containing a simple dependency injection container that is optimized for web apps.
Home-page: https://gitlab.com/tcucco/web-di
Author: Trey Cucco
Author-email: fcucco@gmail.com
License: MIT
Download-URL: https://gitlab.com/tcucco/web-di/-/archive/master/web-di-master.tar.gz
Platform: any
Classifier: Development Status :: 4 - Beta
Classifier: Intended Audience :: Developers
Classifier: License :: OSI Approved :: MIT License
Classifier: Natural Language :: English
Classifier: Operating System :: OS Independent
Classifier: Programming Language :: Python :: 3.8
